summony/__init__.py
summony/loggers.py
summony/py.typed
summony/utils.py
summony/agents/__init__.py
summony/agents/agents.py
summony/agents/anthropic_agent.py
summony/agents/dummy_agent.py
summony/agents/factory.py
summony/agents/gemini_agent.py
summony/agents/ollama_agent.py
summony/agents/openai_agent.py
summony/agents/serialization.py
summony/model_connectors/__init__.py
summony/model_connectors/anthropic_model_connector.py
summony/model_connectors/dummy_model_connector.py
summony/model_connectors/gemini_model_connector.py
summony/model_connectors/model_connectors.py
summony/model_connectors/ollama_model_connector.py
summony/model_connectors/openai_model_connector.py
summony/model_connectors/dummy_model_connector_data/simple/2024-10-05_21-28-01-766271_9c135caa.json
summony/model_connectors/dummy_model_connector_data/simple/2024-10-05_21-28-02-575821_39e4936d.json
summony/model_connectors/dummy_model_connector_data/simple/2024-10-05_21-28-03-087132_977f2fa0.json
summony/model_connectors/dummy_model_connector_data/simple/2024-10-05_21-28-03-638176_c511a9ae.json
summony/model_connectors/dummy_model_connector_data/streaming/2024-10-05_21-22-37-956804_18655314.json
summony/model_connectors/dummy_model_connector_data/streaming/2024-10-05_21-22-38-496640_c4e20cc1.json
summony/model_connectors/dummy_model_connector_data/streaming/2024-10-05_21-22-39-191841_71dbd1cf.json
summony/model_connectors/dummy_model_connector_data/streaming/2024-10-05_21-22-39-805467_99d5b997.json
summony/uis/nbui.py
summony-0.1.2.dist-info/METADATA
summony-0.1.2.dist-info/WHEEL
summony-0.1.2.dist-info/RECORD
