Metadata-Version: 2.3
Name: summony
Version: 0.1.2
Summary: Collection of tools and UIs for chatting and experimenting with multiple LLMs (via their APIs) at the same time.
Requires-Python: >=3.9
Requires-Dist: dataclasses-json>=0.6.7
Requires-Dist: ipywidgets>=8.1.5
Requires-Dist: python-dotenv>=1.0.1
Provides-Extra: anthropic
Requires-Dist: anthropic>=0.36.0; extra == 'anthropic'
Provides-Extra: google
Requires-Dist: google-generativeai>=0.8.3; extra == 'google'
Provides-Extra: groq
Requires-Dist: groq>=0.11.0; extra == 'groq'
Provides-Extra: ollama
Requires-Dist: ollama>=0.3.3; extra == 'ollama'
Provides-Extra: openai
Requires-Dist: openai>=1.51.2; extra == 'openai'
